[
  {
    "name": "Ready for some football?",
    "canonical": "fast && strong",
    "answer": "fast&&strong",
    "correct": true,
    "timestamp": 1661895904996
  },
  {
    "name": "Having fun?",
    "canonical": "done || !fun",
    "answer": "done||fun",
    "correct": false,
    "timestamp": 1661895917420
  },
  {
    "name": "Having fun?",
    "canonical": "done || !fun",
    "answer": "done||!fun",
    "correct": true,
    "timestamp": 1661895924388
  },
  {
    "name": "Wait for a sale?",
    "canonical": "!storeOpen || !isASale",
    "answer": "!storeOpen&&!isASale",
    "correct": false,
    "timestamp": 1661895948756
  }
]